legolm_commons_genai/__init__.py
legolm_commons_genai/html_service.py
legolm_commons_genai-0.0.2.dist-info/METADATA
legolm_commons_genai-0.0.2.dist-info/WHEEL
legolm_commons_genai-0.0.2.dist-info/top_level.txt
legolm_commons_genai-0.0.2.dist-info/RECORD
