Metadata-Version: 2.1
Name: legolm_commons_genai
Version: 0.0.2
Requires-Python: >=3.9
Provides-Extra: dev
Requires-Dist: pytest; extra == "dev"
Requires-Dist: pytest-mock; extra == "dev"
